pan/__init__.py
pan/commit.py
pan/config.py
pan/http.py
pan/rc.py
pan/wfapi.py
pan/xapi.py
pan/afapi/__init__.py
pan/afapi/v1_0.py
pan/licapi/__init__.py
pan/licapi/v1.py
pan_python-0.24.0.data/scripts/panafapi.py
pan_python-0.24.0.data/scripts/panconf.py
pan_python-0.24.0.data/scripts/panlicapi.py
pan_python-0.24.0.data/scripts/panwfapi.py
pan_python-0.24.0.data/scripts/panxapi.py
pan_python-0.24.0.dist-info/AUTHORS.rst
pan_python-0.24.0.dist-info/LICENSE.txt
pan_python-0.24.0.dist-info/METADATA
pan_python-0.24.0.dist-info/WHEEL
pan_python-0.24.0.dist-info/top_level.txt
pan_python-0.24.0.dist-info/RECORD
