Metadata-Version: 2.1
Name: pan-python
Version: 0.24.0
Summary: Multi-tool set for Palo Alto Networks PAN-OS, Panorama, WildFire and AutoFocus
Home-page: https://github.com/kevinsteves/pan-python
Author: Kevin Steves
Author-email: kevin.steves@pobox.com
License: ISC
Classifier: Programming Language :: Python :: 3
Classifier: License :: OSI Approved :: ISC License (ISCL)
Requires-Python: >=3.7
License-File: LICENSE.txt
License-File: AUTHORS.rst
